pydactim/__init__.py
pydactim/anonymization.py
pydactim/brain_extraction.py
pydactim/computation.py
pydactim/conversion.py
pydactim/data.py
pydactim/new_transformation.py
pydactim/perfusion.py
pydactim/preprocessing.py
pydactim/sorting.py
pydactim/spectroscopy.py
pydactim/transformation.py
pydactim/utils.py
pydactim/visualization.py
pydactim/models/__init__.py
pydactim/models/mpunet.py
pydactim/viewer/__init__.py
pydactim/viewer/custom.py
pydactim/viewer/main.py
pydactim/viewer/settings.py
pydactim/viewer/utils.py
pydactim/viewer/view_panel.py
pydactim-1.0.18.dist-info/LICENSE
pydactim-1.0.18.dist-info/METADATA
pydactim-1.0.18.dist-info/WHEEL
pydactim-1.0.18.dist-info/top_level.txt
pydactim-1.0.18.dist-info/RECORD
