Metadata-Version: 2.1
Name: pydactim
Version: 1.0.18
Summary: A library to post-process MRI data
Home-page: https://github.com/PierreFayolle/PyDactim
Author: Pierre Fayolle
Author-email: fayollepierre86@gmail.com
License: UNKNOWN
Project-URL: Documentation, https://pydactim.readthedocs.io/en/latest/
Project-URL: Source, https://github.com/PierreFayolle/PyDactim
Project-URL: Download, https://pypi.org/project/PyDactim/#files
Project-URL: Tracker, https://github.com/PierreFayolle/PyDactim/issues
Platform: UNKNOWN
Classifier: Intended Audience :: Science/Research
Classifier: Programming Language :: Python
Classifier: Topic :: Scientific/Engineering
Classifier: Operating System :: Microsoft :: Windows :: Windows 10
Requires-Python: >=3.7
License-File: LICENSE
Requires-Dist: torchio >=0.18.86
Requires-Dist: SimpleITK
Requires-Dist: numpy
Requires-Dist: nibabel
Requires-Dist: matplotlib
Requires-Dist: pydicom >=2.3.1
Requires-Dist: dicom2nifti
Requires-Dist: dipy >=1.7.0
Requires-Dist: scikit-image
Requires-Dist: numba
Requires-Dist: pyside6
Requires-Dist: pyqtgraph
